aws_login/__init__.py
aws_login/aws_adfs.py
aws_login/cli.py
aws_login/config.py
aws_adfs_login_helper-1.0.1.dist-info/METADATA
aws_adfs_login_helper-1.0.1.dist-info/WHEEL
aws_adfs_login_helper-1.0.1.dist-info/entry_points.txt
aws_adfs_login_helper-1.0.1.dist-info/top_level.txt
aws_adfs_login_helper-1.0.1.dist-info/RECORD
